Metadata-Version: 1.1
Name: target-azureblobstorage
Version: 0.1.0
Summary: Singer.io target for extracting data
Home-page: http://singer.io
Author: Stitch
Author-email: UNKNOWN
License: UNKNOWN
Platform: UNKNOWN
Classifier: Programming Language :: Python :: 3 :: Only
